django_pain/__init__.py
django_pain/apps.py
django_pain/constants.py
django_pain/settings.py
django_pain/translation.py
django_pain/urls.py
django_pain/utils.py
django_pain/admin/__init__.py
django_pain/admin/admin.py
django_pain/admin/filters.py
django_pain/admin/forms.py
django_pain/management/__init__.py
django_pain/management/commands/__init__.py
django_pain/management/commands/import_payments.py
django_pain/management/commands/process_payments.py
django_pain/migrations/0001_initial.py
django_pain/migrations/0002_auto_20180510_0838.py
django_pain/migrations/0003_auto_20180515_0905.py
django_pain/migrations/0004_auto_20180605_1228.py
django_pain/migrations/0005_auto_20180606_1416.py
django_pain/migrations/0006_add_bankpayment_uuid.py
django_pain/migrations/0007_generate_bankpayment_uuid.py
django_pain/migrations/0008_fix_bankpayment_uuid.py
django_pain/migrations/0009_auto_20180718_0416.py
django_pain/migrations/__init__.py
django_pain/models/__init__.py
django_pain/models/bank.py
django_pain/parsers/__init__.py
django_pain/parsers/common.py
django_pain/parsers/czechslovak.py
django_pain/parsers/transproc.py
django_pain/processors/__init__.py
django_pain/processors/common.py
django_pain/tests/__init__.py
django_pain/tests/settings.py
django_pain/tests/test_models.py
django_pain/tests/test_utils.py
django_pain/tests/utils.py
django_pain/tests/admin/__init__.py
django_pain/tests/admin/test_admin.py
django_pain/tests/admin/test_filters.py
django_pain/tests/admin/test_forms.py
django_pain/tests/commands/__init__.py
django_pain/tests/commands/test_import_payments.py
django_pain/tests/commands/test_process_payments.py
django_pain/tests/parsers/__init__.py
django_pain/tests/parsers/test_czechslovak.py
django_pain/tests/parsers/test_transproc.py
django_pain-0.3.0.dist-info/DESCRIPTION.rst
django_pain-0.3.0.dist-info/METADATA
django_pain-0.3.0.dist-info/RECORD
django_pain-0.3.0.dist-info/WHEEL
django_pain-0.3.0.dist-info/metadata.json
django_pain-0.3.0.dist-info/top_level.txt
djmoney_test/__init__.py
djmoney_test/admin.py
djmoney_test/apps.py
djmoney_test/forms.py
djmoney_test/models.py
djmoney_test/settings.py
djmoney_test/tests.py
