Metadata-Version: 2.0
Name: django-pain
Version: 0.3.0
Summary: Django application for managing bank payments and invoices
Home-page: https://github.com/stinovlas/django-pain
Author: Jan Musílek
Author-email: jan.musilek@nic.cz
License: UNKNOWN
Platform: UNKNOWN
Classifier: Development Status :: 2 - Pre-Alpha
Classifier: Environment :: Web Environment
Classifier: Framework :: Django
Classifier: Framework :: Django :: 1.11
Classifier: Framework :: Django :: 2.0
Classifier: Intended Audience :: Developers
Classifier: License :: OSI Approved :: GNU General Public License v3 (GPLv3)
Classifier: Operating System :: OS Independent
Classifier: Programming Language :: Python
Classifier: Programming Language :: Python :: 3.5
Classifier: Programming Language :: Python :: 3.6
Classifier: Topic :: Internet :: WWW/HTTP
Classifier: Topic :: Internet :: WWW/HTTP :: Dynamic Content
Provides-Extra: test
Provides-Extra: quality
Requires-Dist: Django (>=2.0)
Requires-Dist: django-app-settings
Requires-Dist: django-modeltranslation (>=0.13-beta1)
Requires-Dist: django-money (>=0.14.2)
Requires-Dist: lxml
Provides-Extra: quality
Requires-Dist: flake8; extra == 'quality'
Requires-Dist: isort; extra == 'quality'
Requires-Dist: mypy; extra == 'quality'
Requires-Dist: polint; extra == 'quality'
Requires-Dist: pydocstyle; extra == 'quality'
Provides-Extra: test
Requires-Dist: freezegun; extra == 'test'
Requires-Dist: testfixtures; extra == 'test'
